ytvid/__init__.py
ytvid/downloadtool.py
ytvid-6.0.dist-info/METADATA
ytvid-6.0.dist-info/WHEEL
ytvid-6.0.dist-info/top_level.txt
ytvid-6.0.dist-info/RECORD
