Metadata-Version: 2.1
Name: ytvid
Version: 6.0
Summary: Youtube video downloader
Home-page: https://github.com/mickeydarrenlau/ytvid
Author: Darren Lau Wei Jie
License: MIT
Platform: UNKNOWN
Requires-Dist: youtube-dl
